{
    "0": {
        "rh_cost": 1216531.3788599782,
        "comp_time": 6184.183507680893,
        "lj": [
            [
                0.0,
                0.0,
                0.0,
                0.0,
                0.0,
                0.0,
                0.0,
                0.0,
                0.0,
                0.0
            ],
            [
                0.0,
                0.0,
                0.0,
                0.0,
                586.887934813883,
                3722.829009138529,
                2594.680925268755,
                4092.3909784667894,
                6073.159929747105,
                2328.215493569012
            ],
            [
                0.0,
                0.0,
                0.0,
                0.0,
                0.0,
                0.0,
                0.0,
                0.0,
                0.0,
                0.0
            ],
            [
                0.0,
                0.0,
                0.0,
                0.0,
                1618.8559475534246,
                481.1197158867525,
                27.77388790953895,
                122.33870085848899,
                27.773889991628337,
                27.773887909539297
            ],
            [
                0.0,
                0.0,
                0.0,
                0.0,
                0.0,
                0.0,
                184.11916553081872,
                345.3331332906566,
                0.1297236648662228,
                0.12913259286954437
            ],
            [
                0.0,
                0.0,
                0.0,
                0.0,
                0.0,
                0.0,
                0.0,
                0.0,
                0.0,
                0.0
            ],
            [
                0.0,
                0.0,
                0.0,
                0.0,
                0.0,
                0.0,
                0.0,
                0.0,
                0.0,
                0.0
            ],
            [
                0.0,
                0.0,
                0.0,
                0.0,
                1693.1700389069174,
                5038.1534552449075,
                6980.691096799379,
                14481.287880965918,
                17399.63820308729,
                9376.85709192019
            ],
            [
                0.0,
                0.0,
                0.0,
                0.0,
                101.88915902683374,
                101.88915902683374,
                2985.2897411605118,
                7338.916303869957,
                6778.006091035999,
                6748.78834658523
            ],
            [
                0.0,
                0.0,
                0.0,
                0.0,
                0.0,
                0.0,
                0.0,
                0.0,
                0.0,
                0.0
            ]
        ]
    },
    "1": {
        "rh_cost": 2095781.8272625213,
        "comp_time": 6580.172939777374,
        "lj": [
            [
                0.0,
                0.0,
                0.0,
                0.0,
                0.0,
                0.0,
                0.0,
                0.0,
                0.0,
                0.0
            ],
            [
                0.0,
                0.0,
                0.0,
                0.0,
                2532.9659932033132,
                2560.2271575633704,
                6245.348151497999,
                7958.550088623509,
                9131.335475674161,
                9423.712775386179
            ],
            [
                0.0,
                0.0,
                0.0,
                0.0,
                0.0,
                0.0,
                0.0,
                0.0,
                0.0,
                0.0
            ],
            [
                0.0,
                0.0,
                0.0,
                0.0,
                169.40330905857326,
                6099.1693599464625,
                8560.70153459265,
                8765.441929388377,
                8761.9057899246,
                9321.0
            ],
            [
                0.0,
                0.0,
                0.0,
                0.0,
                0.0,
                1596.6203773043217,
                1810.3729921046781,
                1417.8301208530972,
                4598.027256343484,
                3067.6010017740623
            ],
            [
                0.0,
                0.0,
                0.0,
                0.0,
                0.0,
                0.0,
                0.0,
                0.0,
                0.0,
                0.0
            ],
            [
                0.0,
                0.0,
                0.0,
                0.0,
                0.0,
                0.0,
                0.0,
                0.0,
                0.0,
                0.0
            ],
            [
                0.0,
                0.0,
                0.0,
                0.0,
                1335.1568832044513,
                5296.745009789104,
                12178.126775911287,
                21849.27020014212,
                27658.40027470025,
                32574.0
            ],
            [
                0.0,
                0.0,
                0.0,
                0.0,
                19.692411124194464,
                100.85318606336048,
                171.8134301110132,
                4913.12348227264,
                6292.673303774639,
                7405.50291117801
            ],
            [
                0.0,
                0.0,
                0.0,
                0.0,
                0.0,
                0.0,
                0.0,
                0.0,
                0.0,
                0.0
            ]
        ]
    },
    "2": {
        "rh_cost": 2182392.071079323,
        "comp_time": 7114.906924724579,
        "lj": [
            [
                0.0,
                0.0,
                0.0,
                0.0,
                0.0,
                0.0,
                0.0,
                0.0,
                0.0,
                0.0
            ],
            [
                0.0,
                0.0,
                0.0,
                0.0,
                90.67950320478434,
                2279.508992035042,
                7073.819515919173,
                6500.95149090056,
                6608.208901421161,
                9427.0
            ],
            [
                0.0,
                0.0,
                0.0,
                0.0,
                0.0,
                0.0,
                0.0,
                0.0,
                0.0,
                0.0
            ],
            [
                0.0,
                0.0,
                0.0,
                0.0,
                1926.4291522858289,
                5935.272186292408,
                8344.061288992758,
                9158.83723031269,
                9321.0,
                9220.441838675486
            ],
            [
                0.0,
                0.0,
                0.0,
                0.0,
                247.98587373601302,
                167.52051782800226,
                0.0,
                3721.1050122354122,
                9462.387947267147,
                9660.910317535681
            ],
            [
                0.0,
                0.0,
                0.0,
                0.0,
                0.0,
                0.0,
                0.0,
                0.0,
                0.0,
                0.0
            ],
            [
                0.0,
                0.0,
                0.0,
                0.0,
                0.0,
                0.0,
                0.0,
                0.0,
                0.0,
                0.0
            ],
            [
                0.0,
                0.0,
                0.0,
                0.0,
                1924.4693206187499,
                5815.565541800462,
                12003.670308308541,
                21101.038599807944,
                28101.039841376652,
                32574.0
            ],
            [
                0.0,
                0.0,
                0.0,
                0.0,
                51.34563508394704,
                45.71663713597148,
                73.45833010642383,
                3820.7495604140636,
                7217.298939863156,
                7307.7490819450495
            ],
            [
                0.0,
                0.0,
                0.0,
                0.0,
                0.0,
                0.0,
                0.0,
                0.0,
                0.0,
                0.0
            ]
        ]
    },
    "3": {
        "rh_cost": 2125343.0270577613,
        "comp_time": 7630.690807580948,
        "lj": [
            [
                0.0,
                0.0,
                0.0,
                0.0,
                0.0,
                0.0,
                0.0,
                0.0,
                0.0,
                0.0
            ],
            [
                0.0,
                0.0,
                0.0,
                0.0,
                2107.9828252785264,
                5010.321142360433,
                4894.906103725728,
                7025.59875023663,
                8788.374290369606,
                9427.0
            ],
            [
                0.0,
                0.0,
                0.0,
                0.0,
                0.0,
                0.0,
                0.0,
                0.0,
                0.0,
                0.0
            ],
            [
                0.0,
                0.0,
                0.0,
                0.0,
                282.16872366677325,
                1582.8405639872478,
                2051.6672880803917,
                5511.01726233765,
                9321.0,
                9310.911587419807
            ],
            [
                0.0,
                0.0,
                0.0,
                0.0,
                306.28713789629677,
                129.0109743251376,
                81.32806618028926,
                1166.6361548161985,
                3817.0404838970776,
                5657.0465703724385
            ],
            [
                0.0,
                0.0,
                0.0,
                0.0,
                0.0,
                0.0,
                0.0,
                0.0,
                0.0,
                0.0
            ],
            [
                0.0,
                0.0,
                0.0,
                0.0,
                0.0,
                0.0,
                0.0,
                0.0,
                0.0,
                0.0
            ],
            [
                0.0,
                0.0,
                0.0,
                0.0,
                1539.9565669252163,
                4889.0106149367875,
                10823.17680806339,
                20912.752317248625,
                27691.28785954601,
                30989.75251541353
            ],
            [
                0.0,
                0.0,
                0.0,
                0.0,
                26.984955231157,
                34.451565789103405,
                4671.376294115867,
                5555.990405035699,
                5610.195763723764,
                7420.097675474447
            ],
            [
                0.0,
                0.0,
                0.0,
                0.0,
                0.0,
                0.0,
                0.0,
                0.0,
                0.0,
                0.0
            ]
        ]
    },
    "4": {
        "rh_cost": 1998678.8870807951,
        "comp_time": 8049.805790424347,
        "lj": [
            [
                0.0,
                0.0,
                0.0,
                0.0,
                0.0,
                0.0,
                0.0,
                0.0,
                0.0,
                0.0
            ],
            [
                0.0,
                0.0,
                0.0,
                0.0,
                128.31106352234383,
                2353.9091248955665,
                6832.846480463406,
                8427.525198706708,
                9427.0,
                9427.0
            ],
            [
                0.0,
                0.0,
                0.0,
                0.0,
                0.0,
                0.0,
                0.0,
                0.0,
                0.0,
                0.0
            ],
            [
                0.0,
                0.0,
                0.0,
                0.0,
                3039.4922540680163,
                5152.629781290217,
                4615.162636801218,
                6104.544905505541,
                8895.524770386186,
                9024.495430995581
            ],
            [
                0.0,
                0.0,
                0.0,
                0.0,
                0.0,
                7.4953337240559454,
                55.73771264318017,
                2504.1392302195354,
                1754.3106395162652,
                1242.6454479079885
            ],
            [
                0.0,
                0.0,
                0.0,
                0.0,
                0.0,
                0.0,
                0.0,
                0.0,
                0.0,
                0.0
            ],
            [
                0.0,
                0.0,
                0.0,
                0.0,
                0.0,
                0.0,
                0.0,
                0.0,
                0.0,
                0.0
            ],
            [
                0.0,
                0.0,
                0.0,
                0.0,
                946.303423033665,
                4598.488979620028,
                10602.39854385271,
                20480.02959578413,
                27507.436477786658,
                32574.0
            ],
            [
                0.0,
                0.0,
                0.0,
                0.0,
                35.381363975137205,
                55.683045746129196,
                2042.2124559931376,
                3161.525233045011,
                6311.6176172196565,
                7422.000000000006
            ],
            [
                0.0,
                0.0,
                0.0,
                0.0,
                0.0,
                0.0,
                0.0,
                0.0,
                0.0,
                0.0
            ]
        ]
    },
    "5": {
        "rh_cost": 2180893.1802162775,
        "comp_time": 8488.96038389206,
        "lj": [
            [
                0.0,
                0.0,
                0.0,
                0.0,
                0.0,
                0.0,
                0.0,
                0.0,
                0.0,
                0.0
            ],
            [
                0.0,
                0.0,
                0.0,
                0.0,
                235.50439386390434,
                1336.6397367148948,
                1629.9894844738433,
                7863.41088953312,
                8594.774271353403,
                9344.142940045993
            ],
            [
                0.0,
                0.0,
                0.0,
                0.0,
                0.0,
                0.0,
                0.0,
                0.0,
                0.0,
                0.0
            ],
            [
                0.0,
                0.0,
                0.0,
                0.0,
                1423.2989062064617,
                6183.576274934636,
                8581.330506956901,
                8899.126353855465,
                9307.713255436955,
                9321.0
            ],
            [
                0.0,
                0.0,
                0.0,
                0.0,
                0.0,
                71.6296649278324,
                1898.6640351921726,
                4046.9894824983953,
                5951.9527599542735,
                6261.188482615705
            ],
            [
                0.0,
                0.0,
                0.0,
                0.0,
                0.0,
                0.0,
                0.0,
                0.0,
                0.0,
                0.0
            ],
            [
                0.0,
                0.0,
                0.0,
                0.0,
                0.0,
                0.0,
                0.0,
                0.0,
                0.0,
                0.0
            ],
            [
                0.0,
                0.0,
                0.0,
                0.0,
                2674.191009921975,
                6504.741735331354,
                12468.111306567065,
                21656.77569342242,
                28147.943853879486,
                32541.69533838523
            ],
            [
                0.0,
                0.0,
                0.0,
                0.0,
                35.45993301178951,
                5.786014501861103,
                3443.6728749857543,
                4432.976701292497,
                6394.369993587132,
                7360.881654846443
            ],
            [
                0.0,
                0.0,
                0.0,
                0.0,
                0.0,
                0.0,
                0.0,
                0.0,
                0.0,
                0.0
            ]
        ]
    },
    "6": {
        "rh_cost": 2032895.520938756,
        "comp_time": 8879.950694561005,
        "lj": [
            [
                0.0,
                0.0,
                0.0,
                0.0,
                0.0,
                0.0,
                0.0,
                0.0,
                0.0,
                0.0
            ],
            [
                0.0,
                0.0,
                0.0,
                0.0,
                984.4820048399005,
                2441.621307359335,
                7013.762632445775,
                8841.92669982517,
                9427.0,
                9427.0
            ],
            [
                0.0,
                0.0,
                0.0,
                0.0,
                0.0,
                0.0,
                0.0,
                0.0,
                0.0,
                0.0
            ],
            [
                0.0,
                0.0,
                0.0,
                0.0,
                2189.512748125103,
                6909.569152501629,
                8797.523816756406,
                6910.345742820584,
                6889.013548431322,
                8378.886581306439
            ],
            [
                0.0,
                0.0,
                0.0,
                0.0,
                0.0,
                1099.949467475228,
                2333.2884062998046,
                4926.24305055718,
                7811.01401376228,
                1501.639596600237
            ],
            [
                0.0,
                0.0,
                0.0,
                0.0,
                0.0,
                0.0,
                0.0,
                0.0,
                0.0,
                0.0
            ],
            [
                0.0,
                0.0,
                0.0,
                0.0,
                0.0,
                0.0,
                0.0,
                0.0,
                0.0,
                0.0
            ],
            [
                0.0,
                0.0,
                0.0,
                0.0,
                614.133009328034,
                4305.72748351748,
                11543.125327537153,
                18461.40966781603,
                27095.31333303854,
                32573.182544572825
            ],
            [
                0.0,
                0.0,
                0.0,
                0.0,
                134.79624193224103,
                136.78647923708132,
                171.96297274932863,
                4157.357876502897,
                5567.488284106868,
                7422.0
            ],
            [
                0.0,
                0.0,
                0.0,
                0.0,
                0.0,
                0.0,
                0.0,
                0.0,
                0.0,
                0.0
            ]
        ]
    },
    "7": {
        "rh_cost": 2145858.239542751,
        "comp_time": 9357.7203540802,
        "lj": [
            [
                0.0,
                0.0,
                0.0,
                0.0,
                0.0,
                0.0,
                0.0,
                0.0,
                0.0,
                0.0
            ],
            [
                0.0,
                0.0,
                0.0,
                0.0,
                36.63472802906501,
                11.98310278905908,
                5741.326704429486,
                8794.986360759938,
                9427.0,
                9427.0
            ],
            [
                0.0,
                0.0,
                0.0,
                0.0,
                0.0,
                0.0,
                0.0,
                0.0,
                0.0,
                0.0
            ],
            [
                0.0,
                0.0,
                0.0,
                0.0,
                2473.11698819479,
                6657.332666042617,
                6820.396182159321,
                6649.262956519987,
                9321.0,
                9073.457218583728
            ],
            [
                0.0,
                0.0,
                0.0,
                0.0,
                251.32168385456453,
                680.956624447298,
                1668.8515798996534,
                1129.8305661448398,
                4994.844712160006,
                4898.688887258469
            ],
            [
                0.0,
                0.0,
                0.0,
                0.0,
                0.0,
                0.0,
                0.0,
                0.0,
                0.0,
                0.0
            ],
            [
                0.0,
                0.0,
                0.0,
                0.0,
                0.0,
                0.0,
                0.0,
                0.0,
                0.0,
                0.0
            ],
            [
                0.0,
                0.0,
                0.0,
                0.0,
                1461.7641508035258,
                7497.593136553634,
                13248.488013007993,
                21395.734911668464,
                27436.720223122033,
                32574.00000000001
            ],
            [
                0.0,
                0.0,
                0.0,
                0.0,
                39.54994630450092,
                39.54994630450228,
                48.65999483043501,
                3564.6546539204774,
                6025.1981894628125,
                7422.0
            ],
            [
                0.0,
                0.0,
                0.0,
                0.0,
                0.0,
                0.0,
                0.0,
                0.0,
                0.0,
                0.0
            ]
        ]
    },
    "8": {
        "rh_cost": 2351024.080668003,
        "comp_time": 9826.007711172104,
        "lj": [
            [
                0.0,
                0.0,
                0.0,
                0.0,
                0.0,
                0.0,
                0.0,
                0.0,
                0.0,
                0.0
            ],
            [
                0.0,
                0.0,
                0.0,
                0.0,
                0.0,
                1094.2809027709925,
                6571.699499977685,
                7863.148577046643,
                9427.0,
                9427.0
            ],
            [
                0.0,
                0.0,
                0.0,
                0.0,
                0.0,
                0.0,
                0.0,
                0.0,
                0.0,
                0.0
            ],
            [
                0.0,
                0.0,
                0.0,
                0.0,
                3504.3195979335655,
                7143.720066108891,
                7899.551997010769,
                9055.847537555,
                9140.227085931074,
                9321.0
            ],
            [
                0.0,
                0.0,
                0.0,
                0.0,
                250.47184185013296,
                1630.0974876325636,
                1073.9151101021382,
                3970.9660027032833,
                10111.962884052666,
                11035.132219483654
            ],
            [
                0.0,
                0.0,
                0.0,
                0.0,
                0.0,
                0.0,
                0.0,
                0.0,
                0.0,
                0.0
            ],
            [
                0.0,
                0.0,
                0.0,
                0.0,
                0.0,
                0.0,
                0.0,
                0.0,
                0.0,
                0.0
            ],
            [
                0.0,
                0.0,
                0.0,
                0.0,
                1448.5327217408644,
                6421.618968795409,
                13743.954511420274,
                21456.408494006668,
                28721.43546119165,
                32218.78977226846
            ],
            [
                0.0,
                0.0,
                0.0,
                0.0,
                18.3974210283518,
                84.33020092185735,
                94.60612119320366,
                5108.655777325064,
                6224.48183899675,
                7422.0
            ],
            [
                0.0,
                0.0,
                0.0,
                0.0,
                0.0,
                0.0,
                0.0,
                0.0,
                0.0,
                0.0
            ]
        ]
    },
    "9": {
        "rh_cost": 1727138.5906640897,
        "comp_time": 10342.680575847626,
        "lj": [
            [
                0.0,
                0.0,
                0.0,
                0.0,
                0.0,
                0.0,
                0.0,
                0.0,
                0.0,
                0.0
            ],
            [
                0.0,
                0.0,
                0.0,
                0.0,
                5.194337303836719,
                1547.5339273927548,
                4395.593866085505,
                7296.637528530084,
                8400.217968466643,
                9427.0
            ],
            [
                0.0,
                0.0,
                0.0,
                0.0,
                0.0,
                0.0,
                0.0,
                0.0,
                0.0,
                0.0
            ],
            [
                0.0,
                0.0,
                0.0,
                0.0,
                2155.7435081850185,
                6022.111645028138,
                4596.370311008021,
                4313.6503545218875,
                4275.453558971041,
                4275.911211132618
            ],
            [
                0.0,
                0.0,
                0.0,
                0.0,
                0.0,
                0.0,
                0.0,
                19.303409440290793,
                30.284943929599528,
                26.867114127113965
            ],
            [
                0.0,
                0.0,
                0.0,
                0.0,
                0.0,
                0.0,
                0.0,
                0.0,
                0.0,
                0.0
            ],
            [
                0.0,
                0.0,
                0.0,
                0.0,
                0.0,
                0.0,
                0.0,
                0.0,
                0.0,
                0.0
            ],
            [
                0.0,
                0.0,
                0.0,
                0.0,
                1846.8474861244108,
                6348.384344726523,
                14261.688504831342,
                17923.055016759765,
                22873.116154137013,
                22351.67573269145
            ],
            [
                0.0,
                0.0,
                0.0,
                0.0,
                1.349843039008828,
                12.188352264767738,
                55.01180762915099,
                6884.504157014469,
                6902.562825515855,
                7422.0
            ],
            [
                0.0,
                0.0,
                0.0,
                0.0,
                0.0,
                0.0,
                0.0,
                0.0,
                0.0,
                0.0
            ]
        ]
    },
    "10": {
        "rh_cost": 2297036.816183578,
        "comp_time": 10754.522157907486,
        "lj": [
            [
                0.0,
                0.0,
                0.0,
                0.0,
                0.0,
                0.0,
                0.0,
                0.0,
                0.0,
                0.0
            ],
            [
                0.0,
                0.0,
                0.0,
                0.0,
                376.14611888650376,
                2628.77749712293,
                5420.501240612366,
                8401.377341012714,
                8414.97334193856,
                9131.675241522295
            ],
            [
                0.0,
                0.0,
                0.0,
                0.0,
                0.0,
                0.0,
                0.0,
                0.0,
                0.0,
                0.0
            ],
            [
                0.0,
                0.0,
                0.0,
                0.0,
                1430.474147921081,
                5020.061173772243,
                8293.172141772819,
                8375.496519392262,
                8543.916691055181,
                8510.111764042224
            ],
            [
                0.0,
                0.0,
                0.0,
                0.0,
                202.20099716956867,
                149.25219899369557,
                707.7610913396718,
                4236.070836832528,
                11033.861047327979,
                11030.844274127578
            ],
            [
                0.0,
                0.0,
                0.0,
                0.0,
                0.0,
                0.0,
                0.0,
                0.0,
                0.0,
                0.0
            ],
            [
                0.0,
                0.0,
                0.0,
                0.0,
                0.0,
                0.0,
                0.0,
                0.0,
                0.0,
                0.0
            ],
            [
                0.0,
                0.0,
                0.0,
                0.0,
                2279.075098337306,
                6298.826386003016,
                12735.880602965155,
                23326.93943438238,
                29680.922990314968,
                32574.0
            ],
            [
                0.0,
                0.0,
                0.0,
                0.0,
                0.0,
                100.40555743958608,
                801.2804735677802,
                3016.8595967092997,
                6111.9349351953215,
                7339.764171017515
            ],
            [
                0.0,
                0.0,
                0.0,
                0.0,
                0.0,
                0.0,
                0.0,
                0.0,
                0.0,
                0.0
            ]
        ]
    },
    "11": {
        "rh_cost": 1811321.3063027123,
        "comp_time": 11057.156624794006,
        "lj": [
            [
                0.0,
                0.0,
                0.0,
                0.0,
                0.0,
                0.0,
                0.0,
                0.0,
                0.0,
                0.0
            ],
            [
                0.0,
                0.0,
                0.0,
                0.0,
                1590.233147363466,
                1590.233147363466,
                3865.1901913400525,
                8182.398739404866,
                9427.0,
                9427.0
            ],
            [
                0.0,
                0.0,
                0.0,
                0.0,
                0.0,
                0.0,
                0.0,
                0.0,
                0.0,
                0.0
            ],
            [
                0.0,
                0.0,
                0.0,
                0.0,
                1107.2040221871669,
                0.0,
                0.0,
                0.0,
                6422.81348586641,
                3996.838330294398
            ],
            [
                0.0,
                0.0,
                0.0,
                0.0,
                0.0,
                362.220579985147,
                30.644647972410965,
                0.009704639008730748,
                3116.7780452160587,
                0.009704639009065017
            ],
            [
                0.0,
                0.0,
                0.0,
                0.0,
                0.0,
                0.0,
                0.0,
                0.0,
                0.0,
                0.0
            ],
            [
                0.0,
                0.0,
                0.0,
                0.0,
                0.0,
                0.0,
                0.0,
                0.0,
                0.0,
                0.0
            ],
            [
                0.0,
                0.0,
                0.0,
                0.0,
                1364.3157024779741,
                4917.617176976258,
                10909.224106482265,
                20736.581314861025,
                27856.562505578408,
                32562.467238187288
            ],
            [
                0.0,
                0.0,
                0.0,
                0.0,
                1.2439867156494318,
                4277.188305049071,
                7342.118250191362,
                6960.706974753666,
                6964.579722916042,
                7422.0
            ],
            [
                0.0,
                0.0,
                0.0,
                0.0,
                0.0,
                0.0,
                0.0,
                0.0,
                0.0,
                0.0
            ]
        ]
    },
    "12": {
        "rh_cost": 1675590.576676699,
        "comp_time": 11533.99907875061,
        "lj": [
            [
                0.0,
                0.0,
                0.0,
                0.0,
                0.0,
                0.0,
                0.0,
                0.0,
                0.0,
                0.0
            ],
            [
                0.0,
                0.0,
                0.0,
                0.0,
                337.22954988749274,
                831.4733255547811,
                6251.093429918923,
                7918.400938006685,
                7062.011986505174,
                9302.881834793998
            ],
            [
                0.0,
                0.0,
                0.0,
                0.0,
                0.0,
                0.0,
                0.0,
                0.0,
                0.0,
                0.0
            ],
            [
                0.0,
                0.0,
                0.0,
                0.0,
                1627.3707160304118,
                6067.682359491945,
                5701.989000856759,
                5509.126451993087,
                5192.551189446901,
                5316.16325474229
            ],
            [
                0.0,
                0.0,
                0.0,
                0.0,
                1529.1919619014623,
                1009.2837696628405,
                424.15118089565703,
                2081.6830563260596,
                1061.6250952173723,
                361.7014912169952
            ],
            [
                0.0,
                0.0,
                0.0,
                0.0,
                0.0,
                0.0,
                0.0,
                0.0,
                0.0,
                0.0
            ],
            [
                0.0,
                0.0,
                0.0,
                0.0,
                0.0,
                0.0,
                0.0,
                0.0,
                0.0,
                0.0
            ],
            [
                0.0,
                0.0,
                0.0,
                0.0,
                1846.507095565609,
                5628.1689672473985,
                11607.50590178425,
                17339.410792197694,
                14427.020400017294,
                17232.554907975096
            ],
            [
                0.0,
                0.0,
                0.0,
                0.0,
                13.342211786799957,
                126.56144604967385,
                127.61126033441083,
                3935.5920281718268,
                6311.253328780448,
                7349.543329043093
            ],
            [
                0.0,
                0.0,
                0.0,
                0.0,
                0.0,
                0.0,
                0.0,
                0.0,
                0.0,
                0.0
            ]
        ]
    },
    "13": {
        "rh_cost": 2194822.855647964,
        "comp_time": 12006.977841377258,
        "lj": [
            [
                0.0,
                0.0,
                0.0,
                0.0,
                0.0,
                0.0,
                0.0,
                0.0,
                0.0,
                0.0
            ],
            [
                0.0,
                0.0,
                0.0,
                0.0,
                193.42893548277488,
                1568.029559164981,
                3141.565970844328,
                6436.819104238182,
                8441.33257337628,
                9272.933422740593
            ],
            [
                0.0,
                0.0,
                0.0,
                0.0,
                0.0,
                0.0,
                0.0,
                0.0,
                0.0,
                0.0
            ],
            [
                0.0,
                0.0,
                0.0,
                0.0,
                1314.410899786908,
                4925.722000799803,
                8784.540072305386,
                8760.775642002991,
                8987.930543595236,
                9321.0
            ],
            [
                0.0,
                0.0,
                0.0,
                0.0,
                1823.8279312280647,
                466.5681197806676,
                849.8378632978353,
                8469.156356136107,
                7945.421600513997,
                9391.155017124136
            ],
            [
                0.0,
                0.0,
                0.0,
                0.0,
                0.0,
                0.0,
                0.0,
                0.0,
                0.0,
                0.0
            ],
            [
                0.0,
                0.0,
                0.0,
                0.0,
                0.0,
                0.0,
                0.0,
                0.0,
                0.0,
                0.0
            ],
            [
                0.0,
                0.0,
                0.0,
                0.0,
                2186.9772846265705,
                6730.957086427364,
                13706.21107764256,
                23356.19185345851,
                28421.418786664763,
                32574.0
            ],
            [
                0.0,
                0.0,
                0.0,
                0.0,
                103.18588084846805,
                121.2593714256488,
                1328.7428803997939,
                1352.5266274153182,
                6024.863798699619,
                7358.545106266859
            ],
            [
                0.0,
                0.0,
                0.0,
                0.0,
                0.0,
                0.0,
                0.0,
                0.0,
                0.0,
                0.0
            ]
        ]
    },
    "14": {
        "rh_cost": 2361654.405025953,
        "comp_time": 12510.971098899841,
        "lj": [
            [
                0.0,
                0.0,
                0.0,
                0.0,
                0.0,
                0.0,
                0.0,
                0.0,
                0.0,
                0.0
            ],
            [
                0.0,
                0.0,
                0.0,
                0.0,
                65.7322466966854,
                64.02367913864084,
                4916.70594048945,
                8838.405462067465,
                9018.339726136299,
                9427.0
            ],
            [
                0.0,
                0.0,
                0.0,
                0.0,
                0.0,
                0.0,
                0.0,
                0.0,
                0.0,
                0.0
            ],
            [
                0.0,
                0.0,
                0.0,
                0.0,
                2903.4333032299137,
                7042.343504738481,
                8184.334737014673,
                8364.9708013708,
                8502.080399082048,
                8963.170579938589
            ],
            [
                0.0,
                0.0,
                0.0,
                0.0,
                442.03797622070726,
                1807.1124084614012,
                2244.3033161504386,
                6548.076633144606,
                12081.555664191206,
                12245.22791574381
            ],
            [
                0.0,
                0.0,
                0.0,
                0.0,
                0.0,
                0.0,
                0.0,
                0.0,
                0.0,
                0.0
            ],
            [
                0.0,
                0.0,
                0.0,
                0.0,
                0.0,
                0.0,
                0.0,
                0.0,
                0.0,
                0.0
            ],
            [
                0.0,
                0.0,
                0.0,
                0.0,
                2103.4932191400926,
                6328.40625399231,
                12852.973778204194,
                22257.12059016819,
                28830.931413009865,
                32369.143941208713
            ],
            [
                0.0,
                0.0,
                0.0,
                0.0,
                19.91861011860757,
                37.18010957604692,
                36.990939574228385,
                3084.5713602608616,
                6903.677933323378,
                7422.0
            ],
            [
                0.0,
                0.0,
                0.0,
                0.0,
                0.0,
                0.0,
                0.0,
                0.0,
                0.0,
                0.0
            ]
        ]
    },
    "15": {
        "rh_cost": 1573634.4577955534,
        "comp_time": 12840.020562171936,
        "lj": [
            [
                0.0,
                0.0,
                0.0,
                0.0,
                0.0,
                0.0,
                0.0,
                0.0,
                0.0,
                0.0
            ],
            [
                0.0,
                0.0,
                0.0,
                0.0,
                1688.1666054050345,
                3941.3113185279694,
                6566.052444227361,
                8529.973309601452,
                9427.0,
                7309.089427342249
            ],
            [
                0.0,
                0.0,
                0.0,
                0.0,
                0.0,
                0.0,
                0.0,
                0.0,
                0.0,
                0.0
            ],
            [
                0.0,
                0.0,
                0.0,
                0.0,
                124.69970754552665,
                1265.1692169092184,
                6166.509009771539,
                2245.484397789191,
                1265.1693166647217,
                1265.169216909219
            ],
            [
                0.0,
                0.0,
                0.0,
                0.0,
                0.0,
                0.0,
                1966.2011839078834,
                2070.9205806856107,
                1323.8684446423988,
                2012.476046959549
            ],
            [
                0.0,
                0.0,
                0.0,
                0.0,
                0.0,
                0.0,
                0.0,
                0.0,
                0.0,
                0.0
            ],
            [
                0.0,
                0.0,
                0.0,
                0.0,
                0.0,
                0.0,
                0.0,
                0.0,
                0.0,
                0.0
            ],
            [
                0.0,
                0.0,
                0.0,
                0.0,
                1672.4073426237987,
                3495.0286598691473,
                12601.133970542398,
                20798.07283877246,
                26623.117502353492,
                20757.30957519404
            ],
            [
                0.0,
                0.0,
                0.0,
                0.0,
                20.954199475263476,
                20.954199475263476,
                1.1454340992034986,
                7173.357772498552,
                7382.006276988747,
                7420.335116128523
            ],
            [
                0.0,
                0.0,
                0.0,
                0.0,
                0.0,
                0.0,
                0.0,
                0.0,
                0.0,
                0.0
            ]
        ]
    },
    "16": {
        "rh_cost": 1234015.9116585453,
        "comp_time": 13203.862608909607,
        "lj": [
            [
                0.0,
                0.0,
                0.0,
                0.0,
                0.0,
                0.0,
                0.0,
                0.0,
                0.0,
                0.0
            ],
            [
                0.0,
                0.0,
                0.0,
                0.0,
                1952.0296656241285,
                1952.0296656241285,
                6800.745355759074,
                9427.0,
                3670.0072684755423,
                1952.0296656241276
            ],
            [
                0.0,
                0.0,
                0.0,
                0.0,
                0.0,
                0.0,
                0.0,
                0.0,
                0.0,
                0.0
            ],
            [
                0.0,
                0.0,
                0.0,
                0.0,
                0.0,
                3852.392421513347,
                8468.67748050043,
                3977.45042342803,
                3855.945866195667,
                3852.392421513349
            ],
            [
                0.0,
                0.0,
                0.0,
                0.0,
                0.0,
                302.4430032443086,
                0.0,
                3.4633186493986448,
                3804.9630659003296,
                4.992192485840538
            ],
            [
                0.0,
                0.0,
                0.0,
                0.0,
                0.0,
                0.0,
                0.0,
                0.0,
                0.0,
                0.0
            ],
            [
                0.0,
                0.0,
                0.0,
                0.0,
                0.0,
                0.0,
                0.0,
                0.0,
                0.0,
                0.0
            ],
            [
                0.0,
                0.0,
                0.0,
                0.0,
                2400.20049238885,
                4944.044054304895,
                13051.099662659506,
                23790.250434001475,
                15115.318515415598,
                4944.044054304896
            ],
            [
                0.0,
                0.0,
                0.0,
                0.0,
                3.113714313950054,
                3.113714313950054,
                31.7910969435059,
                7302.184057295931,
                7299.0703429819805,
                3.1137143139490924
            ],
            [
                0.0,
                0.0,
                0.0,
                0.0,
                0.0,
                0.0,
                0.0,
                0.0,
                0.0,
                0.0
            ]
        ]
    },
    "17": {
        "rh_cost": 1818890.2316464263,
        "comp_time": 13594.062046766281,
        "lj": [
            [
                0.0,
                0.0,
                0.0,
                0.0,
                0.0,
                0.0,
                0.0,
                0.0,
                0.0,
                0.0
            ],
            [
                0.0,
                0.0,
                0.0,
                0.0,
                1666.9781338199432,
                4037.147954561756,
                7905.8462700429245,
                8937.966059965858,
                8986.704004610265,
                9426.671156302804
            ],
            [
                0.0,
                0.0,
                0.0,
                0.0,
                0.0,
                0.0,
                0.0,
                0.0,
                0.0,
                0.0
            ],
            [
                0.0,
                0.0,
                0.0,
                0.0,
                0.0,
                69.10858135576163,
                116.05914538713857,
                405.84878415484053,
                124.46806920562935,
                3292.114810111651
            ],
            [
                0.0,
                0.0,
                0.0,
                0.0,
                0.0,
                311.2534706324843,
                341.1652786896505,
                431.431243509997,
                2152.9826623556955,
                757.7120391268207
            ],
            [
                0.0,
                0.0,
                0.0,
                0.0,
                0.0,
                0.0,
                0.0,
                0.0,
                0.0,
                0.0
            ],
            [
                0.0,
                0.0,
                0.0,
                0.0,
                0.0,
                0.0,
                0.0,
                0.0,
                0.0,
                0.0
            ],
            [
                0.0,
                0.0,
                0.0,
                0.0,
                986.5025704331825,
                3910.716325146227,
                11021.095283302891,
                20399.81267137113,
                28051.214041440944,
                32573.23181659969
            ],
            [
                0.0,
                0.0,
                0.0,
                0.0,
                17.908527798968304,
                17.908527798968304,
                271.6782310907446,
                4850.351399246823,
                6412.827578297669,
                7422.0
            ],
            [
                0.0,
                0.0,
                0.0,
                0.0,
                0.0,
                0.0,
                0.0,
                0.0,
                0.0,
                0.0
            ]
        ]
    },
    "18": {
        "rh_cost": 2133960.8435280453,
        "comp_time": 14002.84355711937,
        "lj": [
            [
                0.0,
                0.0,
                0.0,
                0.0,
                0.0,
                0.0,
                0.0,
                0.0,
                0.0,
                0.0
            ],
            [
                0.0,
                0.0,
                0.0,
                0.0,
                843.5517687064005,
                1712.6179476526295,
                6619.954422380681,
                8014.4468910451615,
                8861.123809408848,
                9427.0
            ],
            [
                0.0,
                0.0,
                0.0,
                0.0,
                0.0,
                0.0,
                0.0,
                0.0,
                0.0,
                0.0
            ],
            [
                0.0,
                0.0,
                0.0,
                0.0,
                1064.101353432312,
                3477.31044662746,
                3788.947608866464,
                7706.466963213301,
                7508.890907079678,
                9321.0
            ],
            [
                0.0,
                0.0,
                0.0,
                0.0,
                0.0,
                146.25002701386344,
                123.0107217166754,
                8547.681502595959,
                9427.428431348768,
                10542.887699549405
            ],
            [
                0.0,
                0.0,
                0.0,
                0.0,
                0.0,
                0.0,
                0.0,
                0.0,
                0.0,
                0.0
            ],
            [
                0.0,
                0.0,
                0.0,
                0.0,
                0.0,
                0.0,
                0.0,
                0.0,
                0.0,
                0.0
            ],
            [
                0.0,
                0.0,
                0.0,
                0.0,
                2505.887896233129,
                5542.549275970373,
                11826.784154804112,
                22083.155348239357,
                29176.438824976623,
                32560.47734687042
            ],
            [
                0.0,
                0.0,
                0.0,
                0.0,
                5.1884762106410305,
                5.1884762106410305,
                2900.606353460103,
                2946.1035209656643,
                5975.845341514783,
                7237.83815905851
            ],
            [
                0.0,
                0.0,
                0.0,
                0.0,
                0.0,
                0.0,
                0.0,
                0.0,
                0.0,
                0.0
            ]
        ]
    },
    "19": {
        "rh_cost": 2291747.1040954385,
        "comp_time": 14464.505780220032,
        "lj": [
            [
                0.0,
                0.0,
                0.0,
                0.0,
                0.0,
                0.0,
                0.0,
                0.0,
                0.0,
                0.0
            ],
            [
                0.0,
                0.0,
                0.0,
                0.0,
                115.77721529098322,
                2738.7240185148307,
                4168.556335709266,
                9176.665357528036,
                9427.0,
                9426.762111772885
            ],
            [
                0.0,
                0.0,
                0.0,
                0.0,
                0.0,
                0.0,
                0.0,
                0.0,
                0.0,
                0.0
            ],
            [
                0.0,
                0.0,
                0.0,
                0.0,
                2523.6577851082825,
                3359.066362133971,
                7179.0506055807355,
                9321.0,
                9321.0,
                9263.597541715024
            ],
            [
                0.0,
                0.0,
                0.0,
                0.0,
                578.1549838154903,
                0.0,
                2642.04332898704,
                8322.653876466486,
                9479.549986290254,
                12759.549071816653
            ],
            [
                0.0,
                0.0,
                0.0,
                0.0,
                0.0,
                0.0,
                0.0,
                0.0,
                0.0,
                0.0
            ],
            [
                0.0,
                0.0,
                0.0,
                0.0,
                0.0,
                0.0,
                0.0,
                0.0,
                0.0,
                0.0
            ],
            [
                0.0,
                0.0,
                0.0,
                0.0,
                1355.5736594897094,
                5466.1734126117035,
                11794.911296357499,
                20937.50896865147,
                28462.630221305695,
                32438.591736449212
            ],
            [
                0.0,
                0.0,
                0.0,
                0.0,
                26.295704495524674,
                46.46831834480086,
                1325.1441584580605,
                1348.6408084691025,
                4837.547302028982,
                7422.0
            ],
            [
                0.0,
                0.0,
                0.0,
                0.0,
                0.0,
                0.0,
                0.0,
                0.0,
                0.0,
                0.0
            ]
        ]
    },
    "20": {
        "rh_cost": 2122829.5493130763,
        "comp_time": 14957.771030664444,
        "lj": [
            [
                0.0,
                0.0,
                0.0,
                0.0,
                0.0,
                0.0,
                0.0,
                0.0,
                0.0,
                0.0
            ],
            [
                0.0,
                0.0,
                0.0,
                0.0,
                8.21331946323791,
                2929.068205777538,
                7755.133626756388,
                8565.013484175888,
                8625.171219946096,
                9405.133595035715
            ],
            [
                0.0,
                0.0,
                0.0,
                0.0,
                0.0,
                0.0,
                0.0,
                0.0,
                0.0,
                0.0
            ],
            [
                0.0,
                0.0,
                0.0,
                0.0,
                2403.1677646810854,
                5258.950846287934,
                7745.2230903133795,
                7993.190391720412,
                8039.1217715425155,
                8504.174397850782
            ],
            [
                0.0,
                0.0,
                0.0,
                0.0,
                260.6803398100269,
                834.7552847840572,
                851.2068532301599,
                1082.1211253147114,
                1485.0095148669802,
                3984.745978178578
            ],
            [
                0.0,
                0.0,
                0.0,
                0.0,
                0.0,
                0.0,
                0.0,
                0.0,
                0.0,
                0.0
            ],
            [
                0.0,
                0.0,
                0.0,
                0.0,
                0.0,
                0.0,
                0.0,
                0.0,
                0.0,
                0.0
            ],
            [
                0.0,
                0.0,
                0.0,
                0.0,
                1951.9344092246706,
                6000.7928707952615,
                12374.748302267693,
                21248.09717612161,
                27406.277042273054,
                32563.289812918054
            ],
            [
                0.0,
                0.0,
                0.0,
                0.0,
                48.80316486370206,
                70.58279255953182,
                285.0875443586821,
                2383.8551547154675,
                6430.162819897437,
                7409.05264095809
            ],
            [
                0.0,
                0.0,
                0.0,
                0.0,
                0.0,
                0.0,
                0.0,
                0.0,
                0.0,
                0.0
            ]
        ]
    },
    "21": {
        "rh_cost": 2260136.387615645,
        "comp_time": 15475.145314455032,
        "lj": [
            [
                0.0,
                0.0,
                0.0,
                0.0,
                0.0,
                0.0,
                0.0,
                0.0,
                0.0,
                0.0
            ],
            [
                0.0,
                0.0,
                0.0,
                0.0,
                0.0,
                1364.9819895664004,
                6239.365200206142,
                7371.208097047202,
                7467.408211353485,
                9427.0
            ],
            [
                0.0,
                0.0,
                0.0,
                0.0,
                0.0,
                0.0,
                0.0,
                0.0,
                0.0,
                0.0
            ],
            [
                0.0,
                0.0,
                0.0,
                0.0,
                2020.1540739719233,
                6306.581482177004,
                6064.980979332584,
                8905.032295696537,
                9211.591829007333,
                9321.0
            ],
            [
                0.0,
                0.0,
                0.0,
                0.0,
                196.12242426501402,
                0.0,
                43.474795166129795,
                6845.191498424083,
                11134.958290226727,
                11794.993779291965
            ],
            [
                0.0,
                0.0,
                0.0,
                0.0,
                0.0,
                0.0,
                0.0,
                0.0,
                0.0,
                0.0
            ],
            [
                0.0,
                0.0,
                0.0,
                0.0,
                0.0,
                0.0,
                0.0,
                0.0,
                0.0,
                0.0
            ],
            [
                0.0,
                0.0,
                0.0,
                0.0,
                2244.4908393442092,
                5892.275091452096,
                10786.232170840562,
                22635.898654003402,
                28648.346813905562,
                32573.999999999978
            ],
            [
                0.0,
                0.0,
                0.0,
                0.0,
                124.21985098043591,
                347.7613947534674,
                223.5415437730315,
                1081.737755779886,
                6557.610850099837,
                7422.0
            ],
            [
                0.0,
                0.0,
                0.0,
                0.0,
                0.0,
                0.0,
                0.0,
                0.0,
                0.0,
                0.0
            ]
        ]
    },
    "22": {
        "rh_cost": 2155889.2936647073,
        "comp_time": 15866.895472049713,
        "lj": [
            [
                0.0,
                0.0,
                0.0,
                0.0,
                0.0,
                0.0,
                0.0,
                0.0,
                0.0,
                0.0
            ],
            [
                0.0,
                0.0,
                0.0,
                0.0,
                1442.443490047546,
                2416.347286137104,
                4491.035132713813,
                7854.764306953051,
                8916.732874173047,
                9414.654533146106
            ],
            [
                0.0,
                0.0,
                0.0,
                0.0,
                0.0,
                0.0,
                0.0,
                0.0,
                0.0,
                0.0
            ],
            [
                0.0,
                0.0,
                0.0,
                0.0,
                608.8339223385126,
                4941.079078990251,
                2446.455768133582,
                2472.2114764401367,
                2472.2114764401285,
                2490.2297876040975
            ],
            [
                0.0,
                0.0,
                0.0,
                0.0,
                537.798529876831,
                153.69163764830137,
                20.379710210152655,
                3042.136530853382,
                8159.924023407067,
                12397.844323435587
            ],
            [
                0.0,
                0.0,
                0.0,
                0.0,
                0.0,
                0.0,
                0.0,
                0.0,
                0.0,
                0.0
            ],
            [
                0.0,
                0.0,
                0.0,
                0.0,
                0.0,
                0.0,
                0.0,
                0.0,
                0.0,
                0.0
            ],
            [
                0.0,
                0.0,
                0.0,
                0.0,
                1897.378487076291,
                6651.712736633705,
                13529.65020044803,
                22607.210476575514,
                28917.139221653164,
                32574.0
            ],
            [
                0.0,
                0.0,
                0.0,
                0.0,
                43.767372502692886,
                78.80714292933702,
                1810.6754063487729,
                4751.06731269687,
                7422.0,
                7412.376539508707
            ],
            [
                0.0,
                0.0,
                0.0,
                0.0,
                0.0,
                0.0,
                0.0,
                0.0,
                0.0,
                0.0
            ]
        ]
    },
    "23": {
        "rh_cost": 2600776.8537923447,
        "comp_time": 16311.775199174881,
        "lj": [
            [
                0.0,
                0.0,
                0.0,
                0.0,
                0.0,
                0.0,
                0.0,
                0.0,
                0.0,
                0.0
            ],
            [
                0.0,
                0.0,
                0.0,
                0.0,
                3872.7490706367284,
                3655.7532397877776,
                4074.765443169662,
                8580.188536656959,
                8334.790217980628,
                9427.0
            ],
            [
                0.0,
                0.0,
                0.0,
                0.0,
                0.0,
                0.0,
                0.0,
                0.0,
                0.0,
                0.0
            ],
            [
                0.0,
                0.0,
                0.0,
                0.0,
                275.19857934712496,
                810.0034814072629,
                7815.203457683535,
                8520.956324662098,
                8591.471175644832,
                9308.187426788787
            ],
            [
                0.0,
                0.0,
                0.0,
                0.0,
                0.0,
                3991.120256468186,
                4986.10058494944,
                10438.034377288388,
                12717.30059526243,
                16056.51175863392
            ],
            [
                0.0,
                0.0,
                0.0,
                0.0,
                0.0,
                0.0,
                0.0,
                0.0,
                0.0,
                0.0
            ],
            [
                0.0,
                0.0,
                0.0,
                0.0,
                0.0,
                0.0,
                0.0,
                0.0,
                0.0,
                0.0
            ],
            [
                0.0,
                0.0,
                0.0,
                0.0,
                1265.1751298449865,
                6359.326593961021,
                13147.312617274938,
                22370.317330827176,
                29199.593496838796,
                32574.0
            ],
            [
                0.0,
                0.0,
                0.0,
                0.0,
                23.535215910378813,
                20.50250625190278,
                29.742633200069807,
                1844.0203047743646,
                6363.326158675346,
                7422.0
            ],
            [
                0.0,
                0.0,
                0.0,
                0.0,
                0.0,
                0.0,
                0.0,
                0.0,
                0.0,
                0.0
            ]
        ]
    },
    "24": {
        "rh_cost": 1983632.109486771,
        "comp_time": 16868.13697576523,
        "lj": [
            [
                0.0,
                0.0,
                0.0,
                0.0,
                0.0,
                0.0,
                0.0,
                0.0,
                0.0,
                0.0
            ],
            [
                0.0,
                0.0,
                0.0,
                0.0,
                536.1929346362449,
                5011.042259977136,
                3489.8083086170636,
                6353.487551039634,
                8830.886696391975,
                9372.019642398513
            ],
            [
                0.0,
                0.0,
                0.0,
                0.0,
                0.0,
                0.0,
                0.0,
                0.0,
                0.0,
                0.0
            ],
            [
                0.0,
                0.0,
                0.0,
                0.0,
                1773.4408640582524,
                420.8361231435698,
                394.12647707977544,
                383.15351765346776,
                383.69514298527594,
                399.47348650226957
            ],
            [
                0.0,
                0.0,
                0.0,
                0.0,
                238.42026949449803,
                293.2686669452422,
                0.0,
                244.33904997978274,
                6107.155135148456,
                17097.76029757311
            ],
            [
                0.0,
                0.0,
                0.0,
                0.0,
                0.0,
                0.0,
                0.0,
                0.0,
                0.0,
                0.0
            ],
            [
                0.0,
                0.0,
                0.0,
                0.0,
                0.0,
                0.0,
                0.0,
                0.0,
                0.0,
                0.0
            ],
            [
                0.0,
                0.0,
                0.0,
                0.0,
                1727.204596035264,
                4948.311839741371,
                9396.516640489916,
                12181.879311422197,
                18745.509885990148,
                27793.952386643316
            ],
            [
                0.0,
                0.0,
                0.0,
                0.0,
                17.501392835381207,
                26.21915645809546,
                3732.638608243361,
                6287.588778403185,
                7422.0,
                7422.0
            ],
            [
                0.0,
                0.0,
                0.0,
                0.0,
                0.0,
                0.0,
                0.0,
                0.0,
                0.0,
                0.0
            ]
        ]
    },
    "25": {
        "rh_cost": 3129207.3138685524,
        "comp_time": 17180.460220098495,
        "lj": [
            [
                0.0,
                0.0,
                0.0,
                0.0,
                0.0,
                0.0,
                0.0,
                0.0,
                0.0,
                0.0
            ],
            [
                0.0,
                0.0,
                0.0,
                0.0,
                29.368235131859223,
                3899.478791567715,
                8283.15001215866,
                9093.76725340052,
                9427.0,
                9427.0
            ],
            [
                0.0,
                0.0,
                0.0,
                0.0,
                0.0,
                0.0,
                0.0,
                0.0,
                0.0,
                0.0
            ],
            [
                0.0,
                0.0,
                0.0,
                0.0,
                2532.172140357437,
                2113.1858274049446,
                2566.1603677964345,
                6922.939794354267,
                7943.624488252172,
                7943.624488252171
            ],
            [
                0.0,
                0.0,
                0.0,
                0.0,
                198.91517379104513,
                79.77060610168624,
                0.0,
                3727.1211337624554,
                11043.067936789,
                15463.145058824985
            ],
            [
                0.0,
                0.0,
                0.0,
                0.0,
                0.0,
                0.0,
                0.0,
                0.0,
                0.0,
                0.0
            ],
            [
                0.0,
                0.0,
                0.0,
                0.0,
                0.0,
                0.0,
                0.0,
                0.0,
                0.0,
                0.0
            ],
            [
                0.0,
                0.0,
                0.0,
                0.0,
                1560.044761904837,
                6807.055685706708,
                18635.71964057411,
                26717.99927471625,
                31413.654967244423,
                32574.0
            ],
            [
                0.0,
                0.0,
                0.0,
                0.0,
                0.0,
                6582.630360699097,
                4825.609020461833,
                6765.446773929312,
                7401.680882457557,
                7422.0
            ],
            [
                0.0,
                0.0,
                0.0,
                0.0,
                0.0,
                0.0,
                0.0,
                0.0,
                0.0,
                0.0
            ]
        ]
    },
    "26": {
        "rh_cost": 2286051.617797953,
        "comp_time": 17638.946594953537,
        "lj": [
            [
                0.0,
                0.0,
                0.0,
                0.0,
                0.0,
                0.0,
                0.0,
                0.0,
                0.0,
                0.0
            ],
            [
                0.0,
                0.0,
                0.0,
                0.0,
                594.8869533851889,
                1470.0680041954563,
                3169.232900393522,
                3870.5349144106312,
                7328.063684585375,
                9427.0
            ],
            [
                0.0,
                0.0,
                0.0,
                0.0,
                0.0,
                0.0,
                0.0,
                0.0,
                0.0,
                0.0
            ],
            [
                0.0,
                0.0,
                0.0,
                0.0,
                721.7632153961603,
                5223.867629924196,
                9321.0,
                9321.0,
                9321.0,
                9318.8367292615
            ],
            [
                0.0,
                0.0,
                0.0,
                0.0,
                0.0,
                0.0,
                366.50628689528037,
                6941.117828144905,
                9089.788032394878,
                9374.85200453652
            ],
            [
                0.0,
                0.0,
                0.0,
                0.0,
                0.0,
                0.0,
                0.0,
                0.0,
                0.0,
                0.0
            ],
            [
                0.0,
                0.0,
                0.0,
                0.0,
                0.0,
                0.0,
                0.0,
                0.0,
                0.0,
                0.0
            ],
            [
                0.0,
                0.0,
                0.0,
                0.0,
                2746.8865997223793,
                7303.043269121464,
                13595.131502542654,
                24510.09547089132,
                29416.11459116588,
                32492.5631043066
            ],
            [
                0.0,
                0.0,
                0.0,
                0.0,
                0.0,
                87.99282829096536,
                89.99165760300149,
                4792.714347831368,
                7422.0,
                7422.0
            ],
            [
                0.0,
                0.0,
                0.0,
                0.0,
                0.0,
                0.0,
                0.0,
                0.0,
                0.0,
                0.0
            ]
        ]
    },
    "27": {
        "rh_cost": 2164351.7346077454,
        "comp_time": 17924.697550535202,
        "lj": [
            [
                0.0,
                0.0,
                0.0,
                0.0,
                0.0,
                0.0,
                0.0,
                0.0,
                0.0,
                0.0
            ],
            [
                0.0,
                0.0,
                0.0,
                0.0,
                291.35522571891056,
                4255.061222478374,
                8521.55687903907,
                9415.51887314773,
                9427.0,
                9427.0
            ],
            [
                0.0,
                0.0,
                0.0,
                0.0,
                0.0,
                0.0,
                0.0,
                0.0,
                0.0,
                0.0
            ],
            [
                0.0,
                0.0,
                0.0,
                0.0,
                265.3071978584473,
                2242.567939653188,
                1600.5838991133132,
                1608.9871996378056,
                1744.1949308734854,
                1723.8740313465667
            ],
            [
                0.0,
                0.0,
                0.0,
                0.0,
                0.0,
                0.0,
                0.0,
                237.93465593686824,
                8665.598808188282,
                7564.742604568299
            ],
            [
                0.0,
                0.0,
                0.0,
                0.0,
                0.0,
                0.0,
                0.0,
                0.0,
                0.0,
                0.0
            ],
            [
                0.0,
                0.0,
                0.0,
                0.0,
                0.0,
                0.0,
                0.0,
                0.0,
                0.0,
                0.0
            ],
            [
                0.0,
                0.0,
                0.0,
                0.0,
                3014.1502217516595,
                7353.558895508942,
                18034.56843394152,
                24132.978894221,
                32517.61120612952,
                32529.500454041
            ],
            [
                0.0,
                0.0,
                0.0,
                0.0,
                191.50231728286437,
                207.3508441263314,
                4187.451051587002,
                7422.0,
                7422.0,
                7422.0
            ],
            [
                0.0,
                0.0,
                0.0,
                0.0,
                0.0,
                0.0,
                0.0,
                0.0,
                0.0,
                0.0
            ]
        ]
    },
    "28": {
        "rh_cost": 1885595.208224888,
        "comp_time": 18354.748495817184,
        "lj": [
            [
                0.0,
                0.0,
                0.0,
                0.0,
                0.0,
                0.0,
                0.0,
                0.0,
                0.0,
                0.0
            ],
            [
                0.0,
                0.0,
                0.0,
                0.0,
                1336.401499463178,
                4170.755102732553,
                7483.129882144477,
                8690.25315317557,
                8697.168076298609,
                9427.0
            ],
            [
                0.0,
                0.0,
                0.0,
                0.0,
                0.0,
                0.0,
                0.0,
                0.0,
                0.0,
                0.0
            ],
            [
                0.0,
                0.0,
                0.0,
                0.0,
                17.889851121248153,
                19.03287041618306,
                147.76718071142918,
                39.54945450239322,
                4314.216184946988,
                5663.1298849820905
            ],
            [
                0.0,
                0.0,
                0.0,
                0.0,
                14.184394086881332,
                103.97717318372487,
                52.49120304953227,
                0.0,
                1912.3485471210481,
                1249.683802956898
            ],
            [
                0.0,
                0.0,
                0.0,
                0.0,
                0.0,
                0.0,
                0.0,
                0.0,
                0.0,
                0.0
            ],
            [
                0.0,
                0.0,
                0.0,
                0.0,
                0.0,
                0.0,
                0.0,
                0.0,
                0.0,
                0.0
            ],
            [
                0.0,
                0.0,
                0.0,
                0.0,
                1451.599614811157,
                3738.149001829891,
                12570.927600091265,
                19439.275488068775,
                26363.65389595087,
                32406.733119384775
            ],
            [
                0.0,
                0.0,
                0.0,
                0.0,
                84.13720986113795,
                84.13720986113795,
                2573.682940822116,
                5213.2802279954685,
                7422.0,
                7378.366666288311
            ],
            [
                0.0,
                0.0,
                0.0,
                0.0,
                0.0,
                0.0,
                0.0,
                0.0,
                0.0,
                0.0
            ]
        ]
    },
    "29": {
        "rh_cost": 1706459.4504927797,
        "comp_time": 18703.513921022415,
        "lj": [
            [
                0.0,
                0.0,
                0.0,
                0.0,
                0.0,
                0.0,
                0.0,
                0.0,
                0.0,
                0.0
            ],
            [
                0.0,
                0.0,
                0.0,
                0.0,
                2948.527961072534,
                2948.527961072534,
                6345.811156074208,
                8053.362244616386,
                9292.563080301421,
                9166.429814695519
            ],
            [
                0.0,
                0.0,
                0.0,
                0.0,
                0.0,
                0.0,
                0.0,
                0.0,
                0.0,
                0.0
            ],
            [
                0.0,
                0.0,
                0.0,
                0.0,
                38.92971751810587,
                3106.6311542793314,
                4811.23071975841,
                3137.1292990709126,
                3457.21269628944,
                3072.675757251048
            ],
            [
                0.0,
                0.0,
                0.0,
                0.0,
                0.0,
                0.0,
                8.59083801711885,
                674.0269482814475,
                2845.761906892136,
                5.19552969274319
            ],
            [
                0.0,
                0.0,
                0.0,
                0.0,
                0.0,
                0.0,
                0.0,
                0.0,
                0.0,
                0.0
            ],
            [
                0.0,
                0.0,
                0.0,
                0.0,
                0.0,
                0.0,
                0.0,
                0.0,
                0.0,
                0.0
            ],
            [
                0.0,
                0.0,
                0.0,
                0.0,
                1521.530691817688,
                4660.989312005257,
                14912.769545897814,
                20843.89404096042,
                25699.12702328082,
                24436.407595862558
            ],
            [
                0.0,
                0.0,
                0.0,
                0.0,
                71.5200777597131,
                71.5200777597131,
                1016.6568334273569,
                6877.024543568792,
                7222.436202331503,
                7422.0
            ],
            [
                0.0,
                0.0,
                0.0,
                0.0,
                0.0,
                0.0,
                0.0,
                0.0,
                0.0,
                0.0
            ]
        ]
    },
    "30": {
        "rh_cost": 2262523.997042916,
        "comp_time": 19206.177518606186,
        "lj": [
            [
                0.0,
                0.0,
                0.0,
                0.0,
                0.0,
                0.0,
                0.0,
                0.0,
                0.0,
                0.0
            ],
            [
                0.0,
                0.0,
                0.0,
                0.0,
                36.94650395723131,
                1244.1579971388344,
                3874.725514646275,
                7472.916266735517,
                9427.0,
                9427.0
            ],
            [
                0.0,
                0.0,
                0.0,
                0.0,
                0.0,
                0.0,
                0.0,
                0.0,
                0.0,
                0.0
            ],
            [
                0.0,
                0.0,
                0.0,
                0.0,
                2865.30993701583,
                3929.359877431744,
                8328.540398356474,
                8488.58105991281,
                9262.45464782024,
                9321.0
            ],
            [
                0.0,
                0.0,
                0.0,
                0.0,
                0.0,
                3281.131989829605,
                4264.635513368591,
                9737.39788095349,
                10628.309970623168,
                10802.700017034036
            ],
            [
                0.0,
                0.0,
                0.0,
                0.0,
                0.0,
                0.0,
                0.0,
                0.0,
                0.0,
                0.0
            ],
            [
                0.0,
                0.0,
                0.0,
                0.0,
                0.0,
                0.0,
                0.0,
                0.0,
                0.0,
                0.0
            ],
            [
                0.0,
                0.0,
                0.0,
                0.0,
                2118.0678715733434,
                6782.939000061607,
                14230.890987016639,
                21577.09759876685,
                27750.91256915646,
                32559.377564934366
            ],
            [
                0.0,
                0.0,
                0.0,
                0.0,
                31.319572131851583,
                49.88756937246747,
                86.65182845975019,
                1488.5387388286927,
                5409.762842941912,
                7422.0
            ],
            [
                0.0,
                0.0,
                0.0,
                0.0,
                0.0,
                0.0,
                0.0,
                0.0,
                0.0,
                0.0
            ]
        ]
    },
    "31": {
        "rh_cost": 1872904.976581265,
        "comp_time": 19574.362391233444,
        "lj": [
            [
                0.0,
                0.0,
                0.0,
                0.0,
                0.0,
                0.0,
                0.0,
                0.0,
                0.0,
                0.0
            ],
            [
                0.0,
                0.0,
                0.0,
                0.0,
                1619.9546561994364,
                4525.655714886077,
                7291.0323100212445,
                9229.212627396459,
                9291.799632763656,
                9229.212627396459
            ],
            [
                0.0,
                0.0,
                0.0,
                0.0,
                0.0,
                0.0,
                0.0,
                0.0,
                0.0,
                0.0
            ],
            [
                0.0,
                0.0,
                0.0,
                0.0,
                459.86796233656776,
                566.4979500378503,
                619.5226880614352,
                568.9470986649613,
                2114.779023435314,
                568.9470986649591
            ],
            [
                0.0,
                0.0,
                0.0,
                0.0,
                849.6965375499743,
                631.1841946396695,
                680.2723359640604,
                822.9869904808957,
                6608.595321619433,
                6992.435369740751
            ],
            [
                0.0,
                0.0,
                0.0,
                0.0,
                0.0,
                0.0,
                0.0,
                0.0,
                0.0,
                0.0
            ],
            [
                0.0,
                0.0,
                0.0,
                0.0,
                0.0,
                0.0,
                0.0,
                0.0,
                0.0,
                0.0
            ],
            [
                0.0,
                0.0,
                0.0,
                0.0,
                1233.3827611116806,
                4700.542902708323,
                11896.811064253196,
                18705.745668586984,
                22618.922927115487,
                18705.745668586984
            ],
            [
                0.0,
                0.0,
                0.0,
                0.0,
                40.49714326378488,
                1756.4127216729232,
                4129.528286955728,
                7404.55336962057,
                7412.621361276047,
                7404.553369620569
            ],
            [
                0.0,
                0.0,
                0.0,
                0.0,
                0.0,
                0.0,
                0.0,
                0.0,
                0.0,
                0.0
            ]
        ]
    },
    "32": {
        "rh_cost": 975788.0733251403,
        "comp_time": 19842.63638305664,
        "lj": [
            [
                0.0,
                0.0,
                0.0,
                0.0,
                0.0,
                0.0,
                0.0,
                0.0,
                0.0,
                0.0
            ],
            [
                0.0,
                0.0,
                0.0,
                0.0,
                1553.3582255497802,
                4608.783475058156,
                6116.051156763788,
                2835.9396462131745,
                5532.278725951135,
                75.17447673901192
            ],
            [
                0.0,
                0.0,
                0.0,
                0.0,
                0.0,
                0.0,
                0.0,
                0.0,
                0.0,
                0.0
            ],
            [
                0.0,
                0.0,
                0.0,
                0.0,
                1184.351589691524,
                3424.7705915597253,
                92.57252388664715,
                5.73181720170669,
                477.122184676942,
                0.0
            ],
            [
                0.0,
                0.0,
                0.0,
                0.0,
                0.0,
                0.0,
                0.0,
                0.0,
                0.0,
                0.0
            ],
            [
                0.0,
                0.0,
                0.0,
                0.0,
                0.0,
                0.0,
                0.0,
                0.0,
                0.0,
                0.0
            ],
            [
                0.0,
                0.0,
                0.0,
                0.0,
                0.0,
                0.0,
                0.0,
                0.0,
                0.0,
                0.0
            ],
            [
                0.0,
                0.0,
                0.0,
                0.0,
                569.3941415770279,
                4051.070839022021,
                12559.82332803947,
                15601.733244618907,
                15601.733244618907,
                15601.733244618907
            ],
            [
                0.0,
                0.0,
                0.0,
                0.0,
                58.255546426477316,
                58.255546426477316,
                7095.294327898718,
                7420.336628554837,
                4252.60718134164,
                6866.789153128068
            ],
            [
                0.0,
                0.0,
                0.0,
                0.0,
                0.0,
                0.0,
                0.0,
                0.0,
                0.0,
                0.0
            ]
        ]
    },
    "33": {
        "rh_cost": 1974051.7653879107,
        "comp_time": 20333.229376077652,
        "lj": [
            [
                0.0,
                0.0,
                0.0,
                0.0,
                0.0,
                0.0,
                0.0,
                0.0,
                0.0,
                0.0
            ],
            [
                0.0,
                0.0,
                0.0,
                0.0,
                886.2810260413473,
                3986.63137617958,
                7294.496815893666,
                7689.508388348024,
                9427.0,
                9424.009495859935
            ],
            [
                0.0,
                0.0,
                0.0,
                0.0,
                0.0,
                0.0,
                0.0,
                0.0,
                0.0,
                0.0
            ],
            [
                0.0,
                0.0,
                0.0,
                0.0,
                1772.2997808920616,
                2653.4601911405357,
                2849.503890917552,
                2869.5998283540994,
                2925.8482475390297,
                2869.7664478461593
            ],
            [
                0.0,
                0.0,
                0.0,
                0.0,
                708.0577239355969,
                622.4069828222234,
                206.50015808555585,
                1319.4536424041019,
                4523.730092860263,
                2775.787264351901
            ],
            [
                0.0,
                0.0,
                0.0,
                0.0,
                0.0,
                0.0,
                0.0,
                0.0,
                0.0,
                0.0
            ],
            [
                0.0,
                0.0,
                0.0,
                0.0,
                0.0,
                0.0,
                0.0,
                0.0,
                0.0,
                0.0
            ],
            [
                0.0,
                0.0,
                0.0,
                0.0,
                1151.7433180284947,
                4584.504598814536,
                9505.985922489926,
                22288.412389490684,
                28135.028081564786,
                32296.762572278327
            ],
            [
                0.0,
                0.0,
                0.0,
                0.0,
                51.3681576603175,
                187.69456492347373,
                3372.1194508145522,
                5225.442398265442,
                7246.391402970598,
                7422.0
            ],
            [
                0.0,
                0.0,
                0.0,
                0.0,
                0.0,
                0.0,
                0.0,
                0.0,
                0.0,
                0.0
            ]
        ]
    }
}